quanTest/__init__.py
quanTest/analysis.py
quanTest/data.py
quanTest/diagnostics.py
quanTest/financialTools.py
quanTest/main.py
quanTest/order.py
quanTest/portfolio.py
quanTest/position.py
quanTest/simulation.py
quanTest/symbol.py
quanTest/utils.py
quanTest/writer.py
quanTest/models/__init__.py
quanTest/models/slippage.py
quanTest/models/spread.py
q26_quanTester-0.1.1.dist-info/METADATA
q26_quanTester-0.1.1.dist-info/WHEEL
q26_quanTester-0.1.1.dist-info/top_level.txt
q26_quanTester-0.1.1.dist-info/RECORD
