Metadata-Version: 2.1
Name: q26-quanTester
Version: 0.1.1
Summary: A python package for trading simulation
Home-page: https://github.com/LoannData/Q26_QuanTester.git
Author: Loann Brahimi
Author-email: loann.brahimi@data-sciences.io
License: UNKNOWN
Platform: UNKNOWN
Classifier: Programming Language :: Python :: 3
Classifier: License :: OSI Approved :: MIT License
Classifier: Operating System :: OS Independent
Requires-Python: >=3.6
